ccb_essentials/__init__.py
ccb_essentials/argparse.py
ccb_essentials/constant.py
ccb_essentials/filesystem.py
ccb_essentials/logger.py
ccb_essentials/os.py
ccb_essentials/py.typed
ccb_essentials/signal.py
ccb_essentials/sqlite3.py
ccb_essentials/subprocess.py
ccb_essentials-1.3.0.dist-info/METADATA
ccb_essentials-1.3.0.dist-info/WHEEL
ccb_essentials-1.3.0.dist-info/licenses/LICENSE
ccb_essentials-1.3.0.dist-info/RECORD
