Metadata-Version: 2.4
Name: ccb-essentials
Version: 1.3.0
Summary: Essential tools for Python 3.
Project-URL: Repository, https://github.com/clydecbrown/ccb-essentials
Author-email: Clyde C Brown <clyde.c.brown@pm.me>
License: MIT
License-File: LICENSE
Keywords: argparse,file,logging,path,sqlite3,subprocess,utilities
Classifier: Development Status :: 5 - Production/Stable
Classifier: Intended Audience :: Developers
Classifier: License :: OSI Approved :: MIT License
Classifier: Natural Language :: English
Classifier: Operating System :: OS Independent
Classifier: Programming Language :: Python :: 3.10
Classifier: Programming Language :: Python :: 3.11
Classifier: Programming Language :: Python :: 3.12
Classifier: Programming Language :: Python :: 3.13
Classifier: Programming Language :: Python :: 3.14
Classifier: Topic :: Database :: Database Engines/Servers
Classifier: Topic :: Software Development :: Libraries :: Python Modules
Classifier: Topic :: Utilities
Classifier: Typing :: Typed
Requires-Python: >=3.10
